[
  {
    "id" : "77af0020-e21b-4f8e-8f2a-f68f0ecd8466",
    "prId" : 8124,
    "prUrl" : "https://github.com/digital-asset/daml/pull/8124",
    "prSource" : "GitHub",
    "comments" : [
      {
        "id" : "7dd03f8a-7eae-4f72-a1e9-6d3a79013181",
        "parentId" : null,
        "authorId" : "7ddbf119-9fd4-4e95-b47a-aa60f2648372",
        "body" : "`withApollo<OwnProps>` doesn’t work interestingly. The typechecker seems to need the eta expansion. Otherwise the return type doesn’t get simplified and you end up with two types that should be equal but tsc claims they aren’t.",
        "createdAt" : "2020-12-01T18:41:14Z",
        "updatedAt" : "2020-12-02T08:08:51Z",
        "lastEditedBy" : "7ddbf119-9fd4-4e95-b47a-aa60f2648372",
        "tags" : [
        ]
      }
    ],
    "commit" : "aa8bf41fb31492707fb59b0432a7cb68a3e49ebc",
    "line" : 35,
    "diffHunk" : "@@ -1,1 +115,119 @@\nexport const UI: React.ComponentClass<OwnProps> = compose(\n  (x) => withApollo<OwnProps>(x),\n  withRedux,\n)(Component);"
  }
]