[
  {
    "id" : "d035dcce-55f8-4436-a9b0-5e82a2f16123",
    "prId" : 3207,
    "prUrl" : "https://github.com/digital-asset/daml/pull/3207",
    "prSource" : "GitHub",
    "comments" : [
      {
        "id" : "c8cb5d20-3945-46ba-9859-3d8d37a6c6f7",
        "parentId" : null,
        "authorId" : "eb431011-3221-41ae-bf30-e72dde278004",
        "body" : "@gerolf-da: this fieldshould be used in queries once #3126 is merged.",
        "createdAt" : "2019-10-16T16:36:18Z",
        "updatedAt" : "2019-10-28T11:53:23Z",
        "lastEditedBy" : "eb431011-3221-41ae-bf30-e72dde278004",
        "tags" : [
        ]
      }
    ],
    "commit" : "28bd9d4759b6852330b2524547277ae6809f6843",
    "line" : 10,
    "diffHunk" : "@@ -1,1 +8,12 @@-- to store event related data so that it can be easily retrieved later.\n\nALTER TABLE contracts ADD create_event_id varchar;\n\n"
  }
]