[
  {
    "id" : "927bcf60-57da-4d2d-b51a-69c0e27e0b21",
    "prId" : 5853,
    "prUrl" : "https://github.com/digital-asset/daml/pull/5853",
    "prSource" : "GitHub",
    "comments" : [
      {
        "id" : "933ae5a6-6806-4ca4-82bb-53cb901ebe4c",
        "parentId" : null,
        "authorId" : "11e7ec00-9b2f-47d2-abd0-12246c0f9845",
        "body" : "I didn't try out the Java dependencies, but I guess they should be okay. Someone with knowledge about this should please confirm this. ",
        "createdAt" : "2020-05-05T20:41:45Z",
        "updatedAt" : "2020-05-06T10:28:59Z",
        "lastEditedBy" : "11e7ec00-9b2f-47d2-abd0-12246c0f9845",
        "tags" : [
        ]
      }
    ],
    "commit" : "d8071ffab7d5d4af3cd3889e15c3264f025b48d6",
    "line" : 11,
    "diffHunk" : "@@ -1,1 +103,107 @@\nand for **Java**, add the following **Maven** dependency::\n\n    <dependency>\n      <groupId>com.daml</groupId>"
  }
]