[
  {
    "id" : "97311b37-a6fd-440f-9884-e631fc65015c",
    "prId" : 9967,
    "prUrl" : "https://github.com/digital-asset/daml/pull/9967",
    "prSource" : "GitHub",
    "comments" : [
      {
        "id" : "74765646-e218-4d86-9cc4-4f71a1ec7089",
        "parentId" : null,
        "authorId" : "7ddbf119-9fd4-4e95-b47a-aa60f2648372",
        "body" : "Can you please not reflow this in the same PR. It’s very hard to see what has actually changed.",
        "createdAt" : "2021-06-11T08:10:17Z",
        "updatedAt" : "2021-06-11T08:10:18Z",
        "lastEditedBy" : "7ddbf119-9fd4-4e95-b47a-aa60f2648372",
        "tags" : [
        ]
      }
    ],
    "commit" : "141087c864f9e4cfd3d649d5f1813173122b810c",
    "line" : 6,
    "diffHunk" : "@@ -1,1 +12,16 @@One option for doing that is to represent errors explicitly via\n``Either`` or ``Option`` as shown in :doc:`3_Data`. This approach has\nthe advantage that it is very explicit about which operations are\nallowed to fail without aborting the entire transaction. However, it\nalso has two major downsides. First, it can"
  }
]